bitpacking/__init__.py
bitpacking/bitpacking.py
bitpacking-0.1.0.dist-info/METADATA
bitpacking-0.1.0.dist-info/WHEEL
bitpacking-0.1.0.dist-info/top_level.txt
bitpacking-0.1.0.dist-info/RECORD
