Metadata-Version: 2.4
Name: bitpacking
Version: 0.1.0
Summary: Bit-packing and unpacking integer fields
Author-email: Simon Nieswand <simon.nieswand@gmail.com>
License: GPL-3.0-only
Project-URL: Homepage, https://github.com/nieswand/bitpacking
Project-URL: Repository, https://github.com/nieswand/bitpacking
Project-URL: Issues, https://github.com/nieswand/bitpacking/issues
Classifier: Programming Language :: Python :: 3
Requires-Python: >=3.7
